game_controls/__init__.py
game_controls/feather_joywing.py
game_controls/game_controls_base.py
game_controls/pewpewm4.py
game_controls/picosystem.py
game_controls/pybadge.py
game_controls/pygamer.py
game_controls/usb_hid_controller.py
circuitpython_gamecontrols-1.1.0.dist-info/LICENSE
circuitpython_gamecontrols-1.1.0.dist-info/METADATA
circuitpython_gamecontrols-1.1.0.dist-info/WHEEL
circuitpython_gamecontrols-1.1.0.dist-info/top_level.txt
circuitpython_gamecontrols-1.1.0.dist-info/RECORD
