Metadata-Version: 2.2
Name: circuitpython-gamecontrols
Version: 1.1.0
Summary: An abstraction layer for CircuitPython to access commonly used video game control inputs in a consistent manner across different hardware devices and configurations.
Author-email: Tim C <foamyguy@gmail.com>
License: MIT
Project-URL: Homepage, https://github.com/foamyguy/CircuitPython_GameControls
Keywords: adafruit,blinka,circuitpython,micropython,gamecontrols,game,games,controller,game-controller,konami,videogame,gameboy,game&watch
Classifier: Intended Audience :: Developers
Classifier: Topic :: Software Development :: Libraries
Classifier: Topic :: Software Development :: Embedded Systems
Classifier: Topic :: System :: Hardware
Classifier: License :: OSI Approved :: MIT License
Classifier: Programming Language :: Python :: 3
License-File: LICENSE
Requires-Dist: Adafruit-Blinka
Requires-Dist: adafruit-circuitpython-busdevice
Requires-Dist: adafruit-circuitpython-register
Provides-Extra: optional
Requires-Dist: adafruit-circuitpython-featherwing; extra == "optional"
